captains_log/__init__.py
captains_log-0.1.0.dist-info/WHEEL
captains_log-0.1.0.dist-info/METADATA
captains_log-0.1.0.dist-info/RECORD
