Metadata-Version: 2.1
Name: captains-log
Version: 0.1.0
Summary: Out of this world log system
Home-page: UNKNOWN
License: MIT
Author: Juan Gonzalez
Author-email: jrg2156@gmail.com
Requires-Python: >=3.6,<4.0
Classifier: License :: OSI Approved :: MIT License
Classifier: Programming Language :: Python :: 3
Classifier: Programming Language :: Python :: 3.6
Classifier: Programming Language :: Python :: 3.7
